python_utils/__init__.py
python_utils/src/__init__.py
python_utils/src/auth_functions.py
python_utils/src/base_functions.py
python_utils/src/excel_functions.py
python_utils/src/file_functions.py
python_utils/src/log_message.py
python_utils/src/mysql_functions.py
python_utils/src/project_structure_gen.py
python_utils/test/__init__.py
python_utils/test/test_auth_function.py
python_utils/test/test_base_functions.py
python_utils/test/test_excel_functions.py
python_utils/test/test_file_functions.py
python_utils/test/test_log_message.py
python_utils/test/test_mysql_functions.py
python_utils/test/test_project_structure_gen.py
py_utility_scripts-1.5.2.dist-info/LICENSE
py_utility_scripts-1.5.2.dist-info/METADATA
py_utility_scripts-1.5.2.dist-info/WHEEL
py_utility_scripts-1.5.2.dist-info/top_level.txt
py_utility_scripts-1.5.2.dist-info/RECORD
