Metadata-Version: 2.1
Name: py_utility_scripts
Version: 1.5.2
Summary: A collection of utility scripts for working with files, Excel, logging, and database connections.
Home-page: https://github.com/hirushiharan/python-utility-functions.git
Author: Hirushiharan
Author-email: hirushiharant@gmail.com
License: Apache 2.0
Classifier: Intended Audience :: Developers
Classifier: License :: OSI Approved :: Apache Software License
Classifier: Programming Language :: Python :: 3.11
Classifier: Operating System :: OS Independent
Requires-Python: >=3.11
License-File: LICENSE
Requires-Dist: xlsxwriter
Requires-Dist: openpyxl
Requires-Dist: pandas
Requires-Dist: python-dotenv
Requires-Dist: pydantic-settings
Requires-Dist: mysql-connector-python
Requires-Dist: fastapi
Requires-Dist: uvicorn
Requires-Dist: PyJWT
Requires-Dist: email-validator
Provides-Extra: dev
Requires-Dist: pytest ; extra == 'dev'
Requires-Dist: pytest-asyncio ; extra == 'dev'
Requires-Dist: twine ; extra == 'dev'
